yt_transcript/__init__.py
yt_transcript/cli.py
yt_transcript/core.py
yt_transcript_cli-0.1.2.dist-info/licenses/LICENSE
yt_transcript_cli-0.1.2.dist-info/METADATA
yt_transcript_cli-0.1.2.dist-info/WHEEL
yt_transcript_cli-0.1.2.dist-info/entry_points.txt
yt_transcript_cli-0.1.2.dist-info/top_level.txt
yt_transcript_cli-0.1.2.dist-info/RECORD
