Metadata-Version: 2.4
Name: yt-transcript-cli
Version: 0.1.2
Summary: Fetch YouTube video and playlist transcripts from the command line
Author: kirinmurphy
License-Expression: MIT
Project-URL: Homepage, https://github.com/kirinmurphy/youtube-transcript-cli
Project-URL: Repository, https://github.com/kirinmurphy/youtube-transcript-cli.git
Project-URL: Issues, https://github.com/kirinmurphy/youtube-transcript-cli/issues
Keywords: youtube,transcript,subtitles,cli,playlist
Classifier: Development Status :: 3 - Alpha
Classifier: Intended Audience :: Developers
Classifier: Programming Language :: Python :: 3
Classifier: Programming Language :: Python :: 3.11
Classifier: Programming Language :: Python :: 3.12
Classifier: Programming Language :: Python :: 3.13
Classifier: Topic :: Multimedia :: Video
Classifier: Topic :: Utilities
Requires-Python: >=3.11
License-File: LICENSE
Requires-Dist: youtube-transcript-api>=1.2.3
Requires-Dist: requests>=2.28.0
Dynamic: license-file
